Metadata-Version: 1.1
Name: djongo-celery-results
Version: 0.1.0
Summary: A simple Django app to to integrate djongo and celery.
Home-page: https://gitlab.com/Udalbert/djongo-celery-results
Author: Udalbert
Author-email: udgottschalk@gmail.com
License: UNKNOWN
Keywords: djongo-python,celery-djongo,django-djongo
Platform: UNKNOWN
Classifier: Environment :: Web Environment
Classifier: Framework :: Django
Classifier: Intended Audience :: Developers
Classifier: Operating System :: OS Independent
Classifier: Programming Language :: Python
Classifier: Programming Language :: Python :: 3
Classifier: Programming Language :: Python :: 3.2
Classifier: Programming Language :: Python :: 3.3
